{
  "schema_version": 1,
  "generated_at": "2026-06-26T19:31:35Z",
  "declaration_hash": "939f292be4eada7774bfd44d6349d73999206d1d398835c650850f0e1092cfa1",
  "signals": [
    {
      "type_name": "RefVerifyAggregateService",
      "kind_tag": "application_service",
      "signal": "blue",
      "found_type": true
    },
    {
      "type_name": "RefVerifyChainFilter",
      "kind_tag": "enum",
      "signal": "blue",
      "found_type": true,
      "found_items": [
        "core::clone::Clone",
        "core::cmp::Eq",
        "core::cmp::PartialEq",
        "core::fmt::Debug"
      ]
    },
    {
      "type_name": "RefVerifyLaneSummary",
      "kind_tag": "dto",
      "signal": "blue",
      "found_type": true,
      "found_items": [
        "core::clone::Clone",
        "core::fmt::Debug"
      ]
    },
    {
      "type_name": "RefVerifyLayerFilter",
      "kind_tag": "enum",
      "signal": "blue",
      "found_type": true,
      "found_items": [
        "core::clone::Clone",
        "core::cmp::Eq",
        "core::cmp::PartialEq",
        "core::fmt::Debug"
      ]
    },
    {
      "type_name": "RefVerifyPair",
      "kind_tag": "value_object",
      "signal": "blue",
      "found_type": true
    },
    {
      "type_name": "RefVerifyPairRecord",
      "kind_tag": "dto",
      "signal": "blue",
      "found_type": true,
      "found_items": [
        "core::clone::Clone",
        "core::fmt::Debug"
      ]
    },
    {
      "type_name": "RefVerifyResultsOutput",
      "kind_tag": "dto",
      "signal": "blue",
      "found_type": true,
      "found_items": [
        "core::fmt::Debug"
      ]
    },
    {
      "type_name": "RefVerifyVerdictFilter",
      "kind_tag": "enum",
      "signal": "blue",
      "found_type": true,
      "found_items": [
        "core::clone::Clone",
        "core::cmp::Eq",
        "core::cmp::PartialEq",
        "core::fmt::Debug"
      ]
    },
    {
      "type_name": "RefVerifyError",
      "kind_tag": "error_type",
      "signal": "blue",
      "found_type": true
    }
  ]
}
