{
  "schema_version": 2,
  "version": "1.0",
  "title": "`#[doc(hidden)]` 属性の宣言を syn AST 走査で一律禁止する",
  "goal": [
    {
      "id": "GO-01",
      "text": "新サブコマンド `sotp verify doc-hidden` を導入し、workspace の全 crate ソースから `#[doc(hidden)]` 相当の属性宣言を syn AST 走査で検出して CI (`ci-local`) でブロックする。スコープは `architecture-rules.json` の `layers[]` を実行時に読み取ることで自動的に全層に及ぶ。",
      "adr_refs": [
        {
          "file": "knowledge/adr/2026-06-26-0810-prohibit-doc-hidden-attribute.md",
          "anchor": "D2"
        },
        {
          "file": "knowledge/adr/2026-06-26-0810-prohibit-doc-hidden-attribute.md",
          "anchor": "D1"
        }
      ]
    },
    {
      "id": "GO-02",
      "text": "`#[doc(hidden)]` に起因する TDDD chain ③ の DanglingId 副作用検出（エラーメッセージが不明瞭で根本原因を伝えられない）を、属性名を明示する専用ゲートエラーに置き換え、開発者がメッセージを見た時点で対処方針（属性を外すか item を削除する）を判断できるようにする。",
      "adr_refs": [
        {
          "file": "knowledge/adr/2026-06-26-0810-prohibit-doc-hidden-attribute.md",
          "anchor": "D2"
        }
      ]
    }
  ],
  "scope": {
    "in_scope": [
      {
        "id": "IN-01",
        "text": "新 `sotp verify doc-hidden` サブコマンドの追加と、`Makefile.toml` の `ci-local` dependencies への組み込み。`VerifyCommand` enum バリアント / dispatch / gate-name ラベル / `verify/mod.rs` への公開 / `verify-doc-hidden-local` Makefile タスク配線を含む。",
        "adr_refs": [
          {
            "file": "knowledge/adr/2026-06-26-0810-prohibit-doc-hidden-attribute.md",
            "anchor": "D2"
          }
        ]
      },
      {
        "id": "IN-02",
        "text": "以下の全形式の `#[doc(hidden)]` 相当属性の syn AST 検出: 直接の outer `#[doc(hidden)]`、直接の inner `#![doc(hidden)]`、複合 doc 引数（順序不問）`#[doc(hidden, alias = \"x\")]` / `#[doc(alias = \"x\", hidden)]`、`cfg_attr` 包み outer `#[cfg_attr(pred, doc(hidden))]` / `#[cfg_attr(pred, doc(hidden, ...))]`、`cfg_attr` 包み inner `#![cfg_attr(pred, doc(hidden))]`。`#[doc = \"...\"]` name-value 形式は対象外とする。",
        "adr_refs": [
          {
            "file": "knowledge/adr/2026-06-26-0810-prohibit-doc-hidden-attribute.md",
            "anchor": "D2"
          }
        ]
      },
      {
        "id": "IN-03",
        "text": "`#[cfg(test)]` または `#[test]` で gated された item のスキャン除外。既存 `syn_helpers.rs` の `has_cfg_test_attr` を流用し、テストコードは検出対象としない。",
        "adr_refs": [
          {
            "file": "knowledge/adr/2026-06-26-0810-prohibit-doc-hidden-attribute.md",
            "anchor": "D2"
          },
          {
            "file": "knowledge/adr/2026-06-26-0810-prohibit-doc-hidden-attribute.md",
            "anchor": "D1"
          }
        ]
      },
      {
        "id": "IN-04",
        "text": "`libs/infrastructure/src/verify/` 配下に共通 syn 走査ヘルパ（`.rs` ファイル再帰発見 → `syn::parse_file` → `#[cfg(test)]` / `#[test]` 除外 → コールバック visitor による判定）を新設する。既存 `syn_helpers.rs` の `has_cfg_test_attr` を再利用し、判定ロジックはコールバックで受ける設計とする。後続の syn ベース lint（例: `Result<_, String>` 禁止）でも再利用できる粒度とする。",
        "adr_refs": [
          {
            "file": "knowledge/adr/2026-06-26-0810-prohibit-doc-hidden-attribute.md",
            "anchor": "D1"
          }
        ]
      },
      {
        "id": "IN-05",
        "text": "ゲートの有効化スコープを `architecture-rules.json` の `layers[]` から実行時に取得する。per-layer フラグや特定 crate パスのハードコードは持たず、`layers[]` に新 crate が追加されれば自動的に対象に含まれる。",
        "adr_refs": [
          {
            "file": "knowledge/adr/2026-06-26-0810-prohibit-doc-hidden-attribute.md",
            "anchor": "D2"
          }
        ]
      }
    ],
    "out_of_scope": [
      {
        "id": "OS-01",
        "text": "既存 verify ゲート（`usecase-purity` / `domain-purity` / `canonical-modules` / type-signals）への変更・相乗り。本トラックは独立サブコマンドの新設にとどまり、既存ゲートのロジック・インターフェースには触れない。既存ゲートを共通走査基盤へ乗せ替える将来的な改善も対象外とする。",
        "adr_refs": [
          {
            "file": "knowledge/adr/2026-06-26-0810-prohibit-doc-hidden-attribute.md",
            "anchor": "D3"
          }
        ]
      },
      {
        "id": "OS-02",
        "text": "per-layer（per-crate）ごとのゲート有効・無効フラグ。スコープは `layers[]` で一律に決まり、個別ハードコードや設定による除外機構は提供しない。",
        "adr_refs": [
          {
            "file": "knowledge/adr/2026-06-26-0810-prohibit-doc-hidden-attribute.md",
            "anchor": "D2"
          }
        ]
      },
      {
        "id": "OS-03",
        "text": "有効可視性（effective visibility）解析に基づく `pub` item 限定検出。impl block 属性伝播 / pub-reachable 集合 / cross-file `pub use` 再エクスポートグラフ / `#[path]` を辿るモジュール解決などのサブ問題を伴う。可視性不問の一律禁止によりこれらのサブ問題をすべて回避する。",
        "adr_refs": [
          {
            "file": "knowledge/adr/2026-06-26-0810-prohibit-doc-hidden-attribute.md",
            "anchor": "D2"
          }
        ]
      },
      {
        "id": "OS-04",
        "text": "既存コードベースに存在する `#[doc(hidden)]` の cleanup（attribute 除去 / item 削除）。cleanup の要否確認（grep による実例の有無の確認）と実施は実装着手時の別作業であり、本 spec のゲート導入とは切り離す。",
        "adr_refs": [
          {
            "file": "knowledge/adr/2026-06-26-0810-prohibit-doc-hidden-attribute.md",
            "anchor": "D3"
          }
        ]
      },
      {
        "id": "OS-05",
        "text": "dylint カスタム lint による実装。`#[doc(hidden)]` 検出に rustc HIR / 型解決は不要であり、stable syn AST 走査で十分。dylint は nightly `rustc_private` 依存でオーバースペックとなる。",
        "adr_refs": [
          {
            "file": "knowledge/adr/2026-06-26-0810-prohibit-doc-hidden-attribute.md",
            "anchor": "D2"
          }
        ]
      }
    ]
  },
  "constraints": [
    {
      "id": "CN-01",
      "text": "検出ロジックは syn AST 走査で実装する。行ベースの raw text regex は使わない。syn パースにより comment / 文字列リテラル / トークン境界を正確に扱い、複数行属性や `cfg_attr` 絡みの偽陽性・偽陰性を構造的に排除する。",
      "adr_refs": [
        {
          "file": "knowledge/adr/2026-06-26-0810-prohibit-doc-hidden-attribute.md",
          "anchor": "D1"
        },
        {
          "file": "knowledge/adr/2026-06-26-0810-prohibit-doc-hidden-attribute.md",
          "anchor": "D2"
        }
      ]
    },
    {
      "id": "CN-02",
      "text": "検出は可視性（`pub` / `pub(crate)` / 非 pub）を問わず全 item に適用する。有効可視性の機械解析は行わず、属性の有無のみで判定する。",
      "adr_refs": [
        {
          "file": "knowledge/adr/2026-06-26-0810-prohibit-doc-hidden-attribute.md",
          "anchor": "D2"
        }
      ]
    },
    {
      "id": "CN-03",
      "text": "ゲートのスコープは `architecture-rules.json` の `layers[]` を実行時に参照して決定する。特定 crate のパスや名前をコードにハードコードしない。`layers[]` に新 crate が追加されれば自動的にスコープに含まれる（per-layer フラグなし）。",
      "adr_refs": [
        {
          "file": "knowledge/adr/2026-06-26-0810-prohibit-doc-hidden-attribute.md",
          "anchor": "D2"
        }
      ]
    },
    {
      "id": "CN-04",
      "text": "既存の verify ゲート（`usecase_purity` / `canonical_modules` / type-signals 等）のロジックおよびインターフェースに変更を加えない。共通走査ヘルパを新設するが、既存ゲートを共通基盤へ乗せ替えることは本トラックのスコープ外とする。",
      "adr_refs": [
        {
          "file": "knowledge/adr/2026-06-26-0810-prohibit-doc-hidden-attribute.md",
          "anchor": "D3"
        }
      ]
    },
    {
      "id": "CN-05",
      "text": "ゲートのエラー出力は `#[doc(hidden)]` 属性の存在をファイルパス・行情報とともに明示するメッセージを含む。DanglingId のように根本原因を隠すメッセージは許容しない。",
      "adr_refs": [
        {
          "file": "knowledge/adr/2026-06-26-0810-prohibit-doc-hidden-attribute.md",
          "anchor": "D2"
        }
      ]
    },
    {
      "id": "CN-06",
      "text": "実装全体は stable Rust toolchain のみで動作する。nightly や dylint の nightly `rustc_private` 依存は使わない。",
      "adr_refs": [
        {
          "file": "knowledge/adr/2026-06-26-0810-prohibit-doc-hidden-attribute.md",
          "anchor": "D2"
        }
      ]
    }
  ],
  "acceptance_criteria": [
    {
      "id": "AC-01",
      "text": "`sotp verify doc-hidden` が `VerifyCommand` enum のバリアントとして登録されており、`#[doc(hidden)]` のないクリーンなソースに対して `[OK] All checks passed.` を出力して exit 0 を返す。",
      "adr_refs": [
        {
          "file": "knowledge/adr/2026-06-26-0810-prohibit-doc-hidden-attribute.md",
          "anchor": "D2"
        }
      ]
    },
    {
      "id": "AC-02",
      "text": "`layers[]` のいずれかの crate の非テストソースに `#[doc(hidden)]` 相当の属性が存在する場合、ゲートが exit non-zero を返し、`#[doc(hidden)]` 属性の存在をファイルパス・行情報とともに示す finding を出力する。",
      "adr_refs": [
        {
          "file": "knowledge/adr/2026-06-26-0810-prohibit-doc-hidden-attribute.md",
          "anchor": "D2"
        }
      ]
    },
    {
      "id": "AC-03",
      "text": "`#[cfg(test)]` または `#[test]` で gated された item 内の `#[doc(hidden)]` はスキャン対象から除外され、finding を出力せずにゲートが pass する。",
      "adr_refs": [
        {
          "file": "knowledge/adr/2026-06-26-0810-prohibit-doc-hidden-attribute.md",
          "anchor": "D2"
        }
      ]
    },
    {
      "id": "AC-04",
      "text": "IN-02 で列挙した全属性形式（outer / inner / 複合 doc 引数（順序不問）/ cfg_attr 包み outer / cfg_attr 包み inner）が AC-02 の検出対象に含まれ、いずれの形式でも finding が出力される。",
      "adr_refs": [
        {
          "file": "knowledge/adr/2026-06-26-0810-prohibit-doc-hidden-attribute.md",
          "anchor": "D2"
        }
      ]
    },
    {
      "id": "AC-05",
      "text": "`verify-doc-hidden-local` タスクが `Makefile.toml` の `ci-local` dependencies 配列に含まれ、`cargo make ci` 実行時にゲートが自動的に走る。",
      "adr_refs": [
        {
          "file": "knowledge/adr/2026-06-26-0810-prohibit-doc-hidden-attribute.md",
          "anchor": "D2"
        }
      ]
    },
    {
      "id": "AC-06",
      "text": "ゲートの走査対象 crate リストが `architecture-rules.json` の `layers[]` を実行時に読み取って決定される。特定 crate パスがコードにハードコードされていない。`layers[]` に新 crate を追加するだけでゲートのスコープが自動的に広がる。",
      "adr_refs": [
        {
          "file": "knowledge/adr/2026-06-26-0810-prohibit-doc-hidden-attribute.md",
          "anchor": "D2"
        }
      ]
    },
    {
      "id": "AC-07",
      "text": "IN-04 で導入した共通走査ヘルパが、後続の syn ベース lint（例: `Result<_, String>` 禁止）から再利用できる設計になっている。具体的には、ファイル再帰発見・`syn::parse_file`・cfg(test) 除外を共通基盤とし、判定ロジックのみをコールバックで差し替えられること。",
      "adr_refs": [
        {
          "file": "knowledge/adr/2026-06-26-0810-prohibit-doc-hidden-attribute.md",
          "anchor": "D1"
        }
      ]
    },
    {
      "id": "AC-08",
      "text": "既存の verify ゲート（`usecase-purity` / `domain-purity` / `canonical-modules`）の実装・インターフェースが変更されておらず、`cargo make ci` でこれらのゲートが引き続き pass する。",
      "adr_refs": [
        {
          "file": "knowledge/adr/2026-06-26-0810-prohibit-doc-hidden-attribute.md",
          "anchor": "D3"
        }
      ]
    }
  ],
  "related_conventions": [
    {
      "file": "knowledge/conventions/coding-principles.md",
      "anchor": "No Panics in Library Code"
    },
    {
      "file": "knowledge/conventions/enforce-by-mechanism.md",
      "anchor": "Rules"
    },
    {
      "file": "knowledge/conventions/hexagonal-architecture.md",
      "anchor": "Layer Dependencies"
    },
    {
      "file": "knowledge/conventions/responsibility-boundary.md",
      "anchor": "Rules"
    },
    {
      "file": "knowledge/conventions/prefer-type-safe-abstractions.md",
      "anchor": "Decision Flow"
    }
  ],
  "signals": {
    "blue": 26,
    "yellow": 0,
    "red": 0
  }
}
