{
  "schema_version": 1,
  "generated_at": "2026-05-19T15:47:35Z",
  "declaration_hash": "38c67d790a1ec6d6a028debc2ddc16cdd5a5ea845116e8b5e70b631a93206dee",
  "signals": [
    {
      "type_name": "ReviewCheckApprovedInteractor",
      "kind_tag": "interactor",
      "signal": "blue",
      "found_type": true,
      "found_items": [
        "ReviewCheckApprovedService"
      ]
    },
    {
      "type_name": "TaskOperationInteractor",
      "kind_tag": "interactor",
      "signal": "blue",
      "found_type": true,
      "found_items": [
        "TaskOperationService"
      ]
    },
    {
      "type_name": "ReviewCheckApprovedService",
      "kind_tag": "application_service",
      "signal": "blue",
      "found_type": true
    },
    {
      "type_name": "TaskOperationService",
      "kind_tag": "application_service",
      "signal": "blue",
      "found_type": true
    }
  ]
}
